_cvxpy_sparsecholesky.cpython-311-darwin.so
_cvxcore.cpython-311-darwin.so
cvxpy/version.py
cvxpy/error.py
cvxpy/__init__.py
cvxpy/settings.py
cvxpy/py.typed
cvxpy/interface/base_matrix_interface.py
cvxpy/interface/__init__.py
cvxpy/interface/matrix_utilities.py
cvxpy/interface/numpy_interface/matrix_interface.py
cvxpy/interface/numpy_interface/sparse_matrix_interface.py
cvxpy/interface/numpy_interface/__init__.py
cvxpy/interface/numpy_interface/ndarray_interface.py
cvxpy/atoms/max.py
cvxpy/atoms/tr_inv.py
cvxpy/atoms/cummax.py
cvxpy/atoms/ptp.py
cvxpy/atoms/dotsort.py
cvxpy/atoms/matrix_frac.py
cvxpy/atoms/cvar.py
cvxpy/atoms/perspective.py
cvxpy/atoms/lambda_max.py
cvxpy/atoms/sigma_max.py
cvxpy/atoms/total_variation.py
cvxpy/atoms/eye_minus_inv.py
cvxpy/atoms/length.py
cvxpy/atoms/sum_smallest.py
cvxpy/atoms/norm1.py
cvxpy/atoms/lambda_sum_smallest.py
cvxpy/atoms/norm.py
cvxpy/atoms/pf_eigenvalue.py
cvxpy/atoms/pnorm.py
cvxpy/atoms/quantum_rel_entr.py
cvxpy/atoms/__init__.py
cvxpy/atoms/sum_largest.py
cvxpy/atoms/lambda_sum_largest.py
cvxpy/atoms/sum_squares.py
cvxpy/atoms/quantum_cond_entr.py
cvxpy/atoms/log_sum_exp.py
cvxpy/atoms/norm_nuc.py
cvxpy/atoms/dist_ratio.py
cvxpy/atoms/mixed_norm.py
cvxpy/atoms/min.py
cvxpy/atoms/quad_over_lin.py
cvxpy/atoms/geo_mean.py
cvxpy/atoms/errormsg.py
cvxpy/atoms/condition_number.py
cvxpy/atoms/axis_atom.py
cvxpy/atoms/stats.py
cvxpy/atoms/lambda_min.py
cvxpy/atoms/von_neumann_entr.py
cvxpy/atoms/norm_inf.py
cvxpy/atoms/one_minus_pos.py
cvxpy/atoms/quad_form.py
cvxpy/atoms/prod.py
cvxpy/atoms/log_det.py
cvxpy/atoms/suppfunc.py
cvxpy/atoms/harmonic_mean.py
cvxpy/atoms/gen_lambda_max.py
cvxpy/atoms/sign.py
cvxpy/atoms/atom.py
cvxpy/atoms/inv_prod.py
cvxpy/atoms/cumprod.py
cvxpy/atoms/gmatmul.py
cvxpy/atoms/affine/concatenate.py
cvxpy/atoms/affine/vec.py
cvxpy/atoms/affine/trace.py
cvxpy/atoms/affine/unary_operators.py
cvxpy/atoms/affine/vstack.py
cvxpy_base-1.7.5.dist-info/RECORD
cvxpy_base-1.7.5.dist-info/WHEEL
cvxpy_base-1.7.5.dist-info/top_level.txt
cvxpy_base-1.7.5.dist-info/METADATA
cvxpy_base-1.7.5.dist-info/licenses/LICENSE
