Metadata-Version: 2.4
Name: cvxpy-base
Version: 1.7.5
Summary: A domain-specific language for modeling convex optimization problems in Python.
Author-email: Steven Diamond <stevend2@stanford.edu>, akshayka@cs.stanford.edu, Eric Chu <echu508@stanford.edu>, Stephen Boyd <boyd@stanford.edu>
License: Apache License, Version 2.0
Project-URL: Homepage, https://github.com/cvxpy/cvxpy
Requires-Python: >=3.9
License-File: LICENSE
Requires-Dist: numpy>=1.22.4
Requires-Dist: scipy>=1.13.0
Provides-Extra: cbc
Requires-Dist: cylp>=0.91.5; extra == "cbc"
Provides-Extra: clarabel
Provides-Extra: cuopt
Requires-Dist: cuopt-cu12>=25.5; extra == "cuopt"
Requires-Dist: nvidia-cuda-runtime-cu12<13.0,>=12.8; extra == "cuopt"
Provides-Extra: cvxopt
Requires-Dist: cvxopt; extra == "cvxopt"
Provides-Extra: diffcp
Requires-Dist: diffcp; extra == "diffcp"
Provides-Extra: ecos
Requires-Dist: ecos; extra == "ecos"
Provides-Extra: ecos-bb
Requires-Dist: ecos; extra == "ecos-bb"
Provides-Extra: glop
Requires-Dist: ortools<9.15,>=9.7; extra == "glop"
Provides-Extra: glpk
Requires-Dist: cvxopt; extra == "glpk"
Provides-Extra: glpk-mi
Requires-Dist: cvxopt; extra == "glpk-mi"
Provides-Extra: gurobi
Requires-Dist: gurobipy; extra == "gurobi"
Provides-Extra: highs
Requires-Dist: highspy; extra == "highs"
Provides-Extra: mosek
Requires-Dist: Mosek; extra == "mosek"
Provides-Extra: osqp
Provides-Extra: pdlp
Requires-Dist: ortools<9.15,>=9.7; extra == "pdlp"
Provides-Extra: piqp
Requires-Dist: piqp; extra == "piqp"
Provides-Extra: proxqp
Requires-Dist: proxsuite; extra == "proxqp"
Provides-Extra: qoco
Requires-Dist: qoco; extra == "qoco"
Provides-Extra: scip
Requires-Dist: PySCIPOpt; extra == "scip"
Provides-Extra: scipy
Requires-Dist: scipy; extra == "scipy"
Provides-Extra: scs
Provides-Extra: xpress
Requires-Dist: xpress>=9.5; extra == "xpress"
Provides-Extra: daqp
Requires-Dist: daqp; extra == "daqp"
Provides-Extra: testing
Requires-Dist: pytest; extra == "testing"
Requires-Dist: hypothesis; extra == "testing"
Provides-Extra: doc
Requires-Dist: sphinx; extra == "doc"
Requires-Dist: sphinxcontrib.jquery; extra == "doc"
Requires-Dist: sphinx-inline-tabs; extra == "doc"
Requires-Dist: sphinx-design; extra == "doc"
Requires-Dist: sphinx-immaterial>=0.11.7; extra == "doc"
Dynamic: license-file
